README.md
setup.py
plotje/__init__.py
plotje/plotje.py
plotje.egg-info/PKG-INFO
plotje.egg-info/SOURCES.txt
plotje.egg-info/dependency_links.txt
plotje.egg-info/requires.txt
plotje.egg-info/top_level.txt